dk/__init__.py
dk/age.py
dk/asciify.py
dk/dkimport.py
dk/dklogger.py
dk/fstr.py
dk/gchart.py
dk/grid.py
dk/iplist.py
dk/proxy.py
dk/text.py
dk/utidy.py
dk/utils.py
dk/collections/OrderedSet.py
dk/collections/__init__.py
dk/collections/invdict.py
dk/collections/mmap.py
dk/collections/pset.py
dk/collections/sdict.py
dk/collections/xmlrec.py
dk/html/__init__.py
dk/html/css.py
dk/html/html.py
dk/html/theme.py
dk/html/uhtml.py
dk/js/__init__.py
dk/js/js.py
dk-1.2.1.dist-info/LICENSE.txt
dk-1.2.1.dist-info/METADATA
dk-1.2.1.dist-info/WHEEL
dk-1.2.1.dist-info/top_level.txt
dk-1.2.1.dist-info/RECORD
