Metadata-Version: 2.1
Name: dk
Version: 1.2.1
Summary: The Datakortet Basic utilities package: `dk`.
Home-page: http://www.github.com/datakortet/dk/
Author: Bjorn Pettersen
Author-email: bp@datakortet.no
License: LGPL
Download-URL: https://www.github.com/datakortet/dk
Platform: UNKNOWN
Classifier: Development Status :: 3 - Alpha
Classifier: Intended Audience :: Developers
Classifier: Programming Language :: Python
Classifier: Programming Language :: Python :: 3
Classifier: Topic :: Software Development :: Libraries
Requires-Dist: ipaddr
